tap_db2/__init__.py
tap_db2/connector.py
tap_db2/stream.py
tap_db2/tap.py
tap_ibm_db2-0.11.0.dist-info/LICENSE
tap_ibm_db2-0.11.0.dist-info/METADATA
tap_ibm_db2-0.11.0.dist-info/WHEEL
tap_ibm_db2-0.11.0.dist-info/entry_points.txt
tap_ibm_db2-0.11.0.dist-info/RECORD
