Metadata-Version: 2.1
Name: tap-ibm-db2
Version: 0.11.0
Summary: `Tap-DB2` is a Singer tap for IBM DB2 data sources.
Home-page: https://meltano.com
License: MIT
Keywords: DB2,IBM DB2,ELT,Meltano,Meltano SDK
Author: Daniel Purtov
Requires-Python: >=3.9
Classifier: Intended Audience :: Developers
Classifier: License :: OSI Approved :: MIT License
Classifier: Operating System :: OS Independent
Classifier: Programming Language :: Python :: 3
Classifier: Programming Language :: Python :: 3.9
Classifier: Programming Language :: Python :: 3.10
Classifier: Programming Language :: Python :: 3.11
Classifier: Programming Language :: Python :: 3.12
Classifier: Programming Language :: Python :: 3.13
Classifier: Programming Language :: Python :: Implementation :: CPython
Requires-Dist: ibm-db-sa (==0.4.1)
Requires-Dist: singer-sdk (==0.42.1)
Requires-Dist: sqlalchemy (==2.0.36)
Project-URL: Documentation, https://github.com/danielptv/tap-db2/blob/main/README.md
Project-URL: Repository, https://github.com/danielptv/tap-db2
